Osdental/__init__.py
Osdental/BlobStorage/Storage.py
Osdental/BlobStorage/__init__.py
Osdental/Database/Connection.py
Osdental/Database/__init__.py
Osdental/Decorators/AuditLog.py
Osdental/Decorators/DecryptedData.py
Osdental/Decorators/__init__.py
Osdental/Encryptor/Aes.py
Osdental/Encryptor/Jwt.py
Osdental/Encryptor/Rsa.py
Osdental/Encryptor/Sha512.py
Osdental/Encryptor/__init__.py
Osdental/Exception/ControlledException.py
Osdental/Exception/__init__.py
Osdental/ExternalHttp/Client.py
Osdental/ExternalHttp/__init__.py
Osdental/Handlers/BlogFileHandler.py
Osdental/Handlers/DBCatalogQuery.py
Osdental/Handlers/DBSecurityQuery.py
Osdental/Handlers/__init__.py
Osdental/InternalHttp/Request.py
Osdental/InternalHttp/Response.py
Osdental/InternalHttp/__init__.py
Osdental/RedisCache/Redis.py
Osdental/RedisCache/__init__.py
Osdental/ServicesBus/ServicesBus.py
Osdental/ServicesBus/TaskQueue.py
Osdental/ServicesBus/__init__.py
Osdental/Utils/Code.py
Osdental/Utils/Constant.py
Osdental/Utils/Logger.py
Osdental/Utils/Message.py
Osdental/Utils/Util.py
Osdental/Utils/__init__.py
Osdental-5.2.2.dist-info/METADATA
Osdental-5.2.2.dist-info/WHEEL
Osdental-5.2.2.dist-info/top_level.txt
Osdental-5.2.2.dist-info/RECORD
